python_pachyderm/__init__.py
python_pachyderm/client.py
python_pachyderm/datum_batching.py
python_pachyderm/errors.py
python_pachyderm/interceptor.py
python_pachyderm/mixin/__init__.py
python_pachyderm/mixin/admin.py
python_pachyderm/mixin/auth.py
python_pachyderm/mixin/debug.py
python_pachyderm/mixin/enterprise.py
python_pachyderm/mixin/health.py
python_pachyderm/mixin/identity.py
python_pachyderm/mixin/license.py
python_pachyderm/mixin/pfs.py
python_pachyderm/mixin/pps.py
python_pachyderm/mixin/transaction.py
python_pachyderm/mixin/version.py
python_pachyderm/mixin/worker.py
python_pachyderm/pfs.py
python_pachyderm/proto/v2/__init__.py
python_pachyderm/proto/v2/admin/__init__.py
python_pachyderm/proto/v2/admin/admin_pb2.py
python_pachyderm/proto/v2/admin/admin_pb2_grpc.py
python_pachyderm/proto/v2/auth/__init__.py
python_pachyderm/proto/v2/auth/auth_pb2.py
python_pachyderm/proto/v2/auth/auth_pb2_grpc.py
python_pachyderm/proto/v2/debug/__init__.py
python_pachyderm/proto/v2/debug/debug_pb2.py
python_pachyderm/proto/v2/debug/debug_pb2_grpc.py
python_pachyderm/proto/v2/enterprise/__init__.py
python_pachyderm/proto/v2/enterprise/enterprise_pb2.py
python_pachyderm/proto/v2/enterprise/enterprise_pb2_grpc.py
python_pachyderm/proto/v2/identity/__init__.py
python_pachyderm/proto/v2/identity/identity_pb2.py
python_pachyderm/proto/v2/identity/identity_pb2_grpc.py
python_pachyderm/proto/v2/license/__init__.py
python_pachyderm/proto/v2/license/license_pb2.py
python_pachyderm/proto/v2/license/license_pb2_grpc.py
python_pachyderm/proto/v2/pfs/__init__.py
python_pachyderm/proto/v2/pfs/pfs_pb2.py
python_pachyderm/proto/v2/pfs/pfs_pb2_grpc.py
python_pachyderm/proto/v2/pps/__init__.py
python_pachyderm/proto/v2/pps/pps_pb2.py
python_pachyderm/proto/v2/pps/pps_pb2_grpc.py
python_pachyderm/proto/v2/proxy/__init__.py
python_pachyderm/proto/v2/proxy/proxy_pb2.py
python_pachyderm/proto/v2/proxy/proxy_pb2_grpc.py
python_pachyderm/proto/v2/task/__init__.py
python_pachyderm-7.6.0.dist-info/LICENSE
python_pachyderm-7.6.0.dist-info/METADATA
python_pachyderm-7.6.0.dist-info/WHEEL
python_pachyderm-7.6.0.dist-info/RECORD
