Metadata-Version: 2.1
Name: python-pachyderm
Version: 7.6.0
Summary: Python Pachyderm Client
Home-page: https://github.com/pachyderm/python-pachyderm
License: Apache 2.0
Keywords: pachyderm
Author: Pachyderm Integrations
Author-email: integrations@pachyderm.io
Requires-Python: >=3.8,<4.0
Classifier: Intended Audience :: Developers
Classifier: License :: OSI Approved :: Apache Software License
Classifier: License :: Other/Proprietary License
Classifier: Programming Language :: Python :: 3
Classifier: Programming Language :: Python :: 3.8
Classifier: Programming Language :: Python :: 3.9
Classifier: Programming Language :: Python :: 3.10
Classifier: Programming Language :: Python :: 3.11
Classifier: Programming Language :: Python :: 3
Classifier: Programming Language :: Python :: 3.10
Classifier: Programming Language :: Python :: 3.11
Classifier: Programming Language :: Python :: 3.8
Classifier: Programming Language :: Python :: 3.9
Classifier: Programming Language :: Python :: Implementation :: CPython
Requires-Dist: grpc-interceptor (>=0.13.0,<0.14.0)
Requires-Dist: grpcio (>=1.54.2)
Requires-Dist: grpcio-health-checking (>=1.38.0)
Requires-Dist: importlib-metadata (>1.5.1) ; python_version < "3.8"
Requires-Dist: protobuf (>=3.17.1,<4.0.0)
Requires-Dist: python-dotenv (>=1.0.0)
Project-URL: Documentation, https://python-pachyderm.readthedocs.io/en/stable/
Project-URL: Repository, https://github.com/pachyderm/python-pachyderm
